{
  "version": 1,
  "serviceConfiguration": {
    "apiName": "municipal",
    "serviceName": "AppSync",
    "defaultAuthType": {
      "mode": "AMAZON_COGNITO_USER_POOLS",
      "cognitoUserPoolId": "authmunicipal6e3c111b"
    },
    "additionalAuthTypes": [
      {
        "mode": "API_KEY",
        "expirationTime": 180,
        "apiKeyExpirationDate": "2025-04-05T13:58:37.972Z",
        "keyDescription": "MuniciPal GraphQL API key"
      }
    ],
    "conflictResolution": {
      "defaultResolutionStrategy": {
        "type": "AUTOMERGE"
      }
    }
  }
}